micrograd/__init__.py
micrograd/draw.py
micrograd/node.py
gradflow_kit-0.1.3.dist-info/METADATA
gradflow_kit-0.1.3.dist-info/WHEEL
gradflow_kit-0.1.3.dist-info/top_level.txt
gradflow_kit-0.1.3.dist-info/RECORD
