Metadata-Version: 2.4
Name: gradflow_kit
Version: 0.1.3
Summary: A clean and modular auto-differentiation engine inspired by micrograd
Home-page: https://github.com/N-T-Raghava/GradFlow
Author: N-T-Raghava
Author-email: tanmairaghav3836@gmail.com
Classifier: Development Status :: 3 - Alpha
Classifier: Intended Audience :: Developers
Classifier: Topic :: Scientific/Engineering :: Artificial Intelligence
Classifier: License :: OSI Approved :: MIT License
Classifier: Programming Language :: Python :: 3
Classifier: Programming Language :: Python :: 3.10
Classifier: Operating System :: OS Independent
Requires-Python: >=3.8
Requires-Dist: graphviz
Dynamic: author
Dynamic: author-email
Dynamic: classifier
Dynamic: description
Dynamic: description-content-type
Dynamic: home-page
Dynamic: requires-dist
Dynamic: requires-python
Dynamic: summary
